thonnycontrib/postit/VERSION
thonnycontrib/postit/__init__.py
thonnycontrib/postit/aiassist.py
thonnycontrib/postit/asset_copy.py
thonnycontrib/postit/base_postit.py
thonnycontrib/postit/block_enclosed_postit.py
thonnycontrib/postit/common.py
thonnycontrib/postit/dropdown_postit.py
thonnycontrib/postit/enclosed_postit.py
thonnycontrib/postit/monkey_patch.py
thonnycontrib/postit/assets/groups_info.json
thonnycontrib/postit/assets/3d_example_texture/categories_info.json
thonnycontrib/postit/assets/3d_example_texture/cube_6face/empty_6face.png
thonnycontrib/postit/assets/3d_example_texture/cube_6face/empty_6face_thumbnail.png
thonnycontrib/postit/assets/3d_example_texture/cube_6face/files_info.json
thonnycontrib/postit/assets/3d_example_texture/cube_6face/head_6face.png
thonnycontrib/postit/assets/3d_example_texture/cube_6face/head_6face_thumbnail.png
thonnycontrib/postit/assets/3d_example_texture/cube_6face/rubik_6face.png
thonnycontrib/postit/assets/3d_example_texture/cube_6face/rubik_6face_thumbnail.png
thonnycontrib/postit/assets/3d_example_texture/frame/crystal_ball.png
thonnycontrib/postit/assets/3d_example_texture/frame/crystal_ball_thumbnail.jpg
thonnycontrib/postit/assets/3d_example_texture/frame/files_info.json
thonnycontrib/postit/assets/3d_example_texture/frame/frame1_4_3.png
thonnycontrib/postit/assets/3d_example_texture/frame/frame1_4_3_thumbnail.jpg
thonnycontrib/postit/assets/3d_example_texture/frame/frame2_16_9.png
thonnycontrib/postit/assets/3d_example_texture/frame/frame2_16_9_thumbnail.jpg
thonnycontrib/postit/assets/3d_example_texture/frame/frame3_16_9.png
thonnycontrib/postit/assets/3d_example_texture/frame/frame3_16_9_thumbnail.jpg
thonnycontrib/postit/assets/3d_example_texture/frame/globe_frame.png
thonnycontrib/postit/assets/3d_example_texture/frame/globe_frame_thumbnail.jpg
thonnycontrib/postit/assets/3d_example_texture/frame/pad_frame_4_3.png
thonnycontrib/postit/assets/3d_example_texture/frame/pad_frame_4_3_thumbnail.jpg
thonny_postit-1.3.4.dist-info/LICENSE
thonny_postit-1.3.4.dist-info/METADATA
thonny_postit-1.3.4.dist-info/WHEEL
thonny_postit-1.3.4.dist-info/top_level.txt
thonny_postit-1.3.4.dist-info/RECORD
