Metadata-Version: 2.1
Name: thonny-postit
Version: 1.3.4
Summary: Program Post-it for Thonny IDE
Home-page: https://github.com/beardad1975/thonny-postit
Author: Wen-Hung, Chang 張文宏
Author-email: beardad1975@nmes.tyc.edu.tw
Platform: Windows
Classifier: Programming Language :: Python :: 3
Classifier: License :: OSI Approved :: MIT License
Classifier: Operating System :: Microsoft :: Windows
Classifier: Natural Language :: Chinese (Traditional)
Requires-Python: >=3.8
License-File: LICENSE
Requires-Dist: thonny (>=4.1.6)
Requires-Dist: pillow (>=9.1.1)
Requires-Dist: pyperclip (>=1.8.2)
Requires-Dist: python-tgpt (==0.7.4)
Requires-Dist: curl-cffi (==0.7.2)
Requires-Dist: cjkwrap (==2.2)
